{"type":"FeatureCollection","metadata":{"generated":1604675240000,"url":"https://earthquake.usgs.gov/earthquakes/feed/v1.0/summary/all_hour.geojson","title":"USGS All Earthquakes, Past Hour","status":200,"api":"1.10.3","count":8},"features":[{"type":"Feature","properties":{"mag":1.42,"place":"21km NNW of Tehachapi, CA","time":1604674148410,"updated":1604674368028,"tz":null,"url":"https://earthquake.usgs.gov/earthquakes/eventpage/ci39459055","detail":"https://earthquake.usgs.gov/earthquakes/feed/v1.0/detail/ci39459055.geojson","felt":null,"cdi":null,"mmi":null,"alert":null,"status":"automatic","tsunami":0,"sig":31,"net":"ci","code":"39459055","ids":",ci39459055,","sources":",ci,","types":",nearby-cities,origin,phase-data,scitech-link,","nst":18,"dmin":0.1383,"rms":0.18,"gap":80,"magType":"ml","type":"earthquake","title":"M 1.4 - 21km NNW of Tehachapi, CA"},"geometry":{"type":"Point","coordinates":[-118.5475,35.3071667,3.12]},"id":"ci39459055"},
{"type":"Feature","properties":{"mag":0.74,"place":"8km W of Cobb, CA","time":1604674051130,"updated":1604674924792,"tz":null,"url":"https://earthquake.usgs.gov/earthquakes/eventpage/nc73478701","detail":"https://earthquake.usgs.gov/earthquakes/feed/v1.0/detail/nc73478701.geojson","felt":null,"cdi":null,"mmi":null,"alert":null,"status":"automatic","tsunami":0,"sig":8,"net":"nc","code":"73478701","ids":",nc73478701,","sources":",nc,","types":",nearby-cities,origin,phase-data,scitech-link,","nst":13,"dmin":0.01233,"rms":0.01,"gap":80,"magType":"md","type":"earthquake","title":"M 0.7 - 8km W of Cobb, CA"},"geometry":{"type":"Point","coordinates":[-122.8118362,38.8356667,1.76]},"id":"nc73478701"},
{"type":"Feature","properties":{"mag":1.63,"place":"7km NE of Aguanga, CA","time":1604673820610,"updated":1604674496130,"tz":null,"url":"https://earthquake.usgs.gov/earthquakes/eventpage/ci39459039","detail":"https://earthquake.usgs.gov/earthquakes/feed/v1.0/detail/ci39459039.geojson","felt":null,"cdi":null,"mmi":null,"alert":null,"status":"automatic","tsunami":0,"sig":41,"net":"ci","code":"39459039","ids":",ci39459039,","sources":",ci,","types":",focal-mechanism,nearby-cities,origin,phase-data,scitech-link,","nst":63,"dmin":0.03451,"rms":0.21,"gap":32,"magType":"ml","type":"earthquake","title":"M 1.6 - 7km NE of Aguanga, CA"},"geometry":{"type":"Point","coordinates":[-116.8051667,33.478,3.13]},"id":"ci39459039"},
{"type":"Feature","properties":{"mag":0.9,"place":"9km W of Corona, CA","time":1604673050080,"updated":1604673280551,"tz":null,"url":"https://earthquake.usgs.gov/earthquakes/eventpage/ci39459031","detail":"https://earthquake.usgs.gov/earthquakes/feed/v1.0/detail/ci39459031.geojson","felt":null,"cdi":null,"mmi":null,"alert":null,"status":"automatic","tsunami":0,"sig":12,"net":"ci","code":"39459031","ids":",ci39459031,","sources":",ci,","types":",nearby-cities,origin,phase-data,scitech-link,","nst":16,"dmin":0.09146,"rms":0.25,"gap":75,"magType":"ml","type":"earthquake","title":"M 0.9 - 9km W of Corona, CA"},"geometry":{"type":"Point","coordinates":[-117.6623333,33.8755,4.75]},"id":"ci39459031"},
{"type":"Feature","properties":{"mag":1.08,"place":"15km NE of Borrego Springs, CA","time":1604672803310,"updated":1604675152677,"tz":null,"url":"https://earthquake.usgs.gov/earthquakes/eventpage/ci39459015","detail":"https://earthquake.usgs.gov/earthquakes/feed/v1.0/detail/ci39459015.geojson","felt":null,"cdi":null,"mmi":null,"alert":null,"status":"reviewed","tsunami":0,"sig":18,"net":"ci","code":"39459015","ids":",ci39459015,","sources":",ci,","types":",nearby-cities,origin,phase-data,scitech-link,","nst":40,"dmin":0.05678,"rms":0.23,"gap":87,"magType":"ml","type":"earthquake","title":"M 1.1 - 15km NE of Borrego Springs, CA"},"geometry":{"type":"Point","coordinates":[-116.2463333,33.3418333,10.56]},"id":"ci39459015"},
{"type":"Feature","properties":{"mag":1.04,"place":"8km SW of Salton City, CA","time":1604672487590,"updated":1604672711939,"tz":null,"url":"https://earthquake.usgs.gov/earthquakes/eventpage/ci39459007","detail":"https://earthquake.usgs.gov/earthquakes/feed/v1.0/detail/ci39459007.geojson","felt":null,"cdi":null,"mmi":null,"alert":null,"status":"automatic","tsunami":0,"sig":17,"net":"ci","code":"39459007","ids":",ci39459007,","sources":",ci,","types":",nearby-cities,origin,phase-data,scitech-link,","nst":29,"dmin":0.1585,"rms":0.21,"gap":86,"magType":"ml","type":"earthquake","title":"M 1.0 - 8km SW of Salton City, CA"},"geometry":{"type":"Point","coordinates":[-116.0071667,33.2393333,1.44]},"id":"ci39459007"},
{"type":"Feature","properties":{"mag":2.5,"place":"31 km SE of Mina, Nevada","time":1604672370690,"updated":1604673493278,"tz":null,"url":"https://earthquake.usgs.gov/earthquakes/eventpage/nn00782112","detail":"https://earthquake.usgs.gov/earthquakes/feed/v1.0/detail/nn00782112.geojson","felt":null,"cdi":null,"mmi":null,"alert":null,"status":"automatic","tsunami":0,"sig":96,"net":"nn","code":"00782112","ids":",nc73478696,nn00782112,","sources":",nc,nn,","types":",nearby-cities,origin,phase-data,scitech-link,","nst":23,"dmin":0.018,"rms":0.11,"gap":73.5,"magType":"ml","type":"earthquake","title":"M 2.5 - 31 km SE of Mina, Nevada"},"geometry":{"type":"Point","coordinates":[-117.8853,38.171,10.9]},"id":"nn00782112"},
{"type":"Feature","properties":{"mag":2.4,"place":"36 km SE of Mina, Nevada","time":1604672013170,"updated":1604672414081,"tz":null,"url":"https://earthquake.usgs.gov/earthquakes/eventpage/nn00782109","detail":"https://earthquake.usgs.gov/earthquakes/feed/v1.0/detail/nn00782109.geojson","felt":null,"cdi":null,"mmi":null,"alert":null,"status":"automatic","tsunami":0,"sig":89,"net":"nn","code":"00782109","ids":",nn00782109,","sources":",nn,","types":",origin,phase-data,","nst":30,"dmin":0.043,"rms":0.09,"gap":74.6,"magType":"ml","type":"earthquake","title":"M 2.4 - 36 km SE of Mina, Nevada"},"geometry":{"type":"Point","coordinates":[-117.795,38.1805,11]},"id":"nn00782109"}],"bbox":[-122.8118362,33.2393333,1.44,-116.0071667,38.8356667,11]}